CHANGELOG.txt
LICENCE.txt
MANIFEST.in
README.txt
setup.py
SilverHandTrackingModule/__init__.py
SilverHandTrackingModule.egg-info/PKG-INFO
SilverHandTrackingModule.egg-info/SOURCES.txt
SilverHandTrackingModule.egg-info/dependency_links.txt
SilverHandTrackingModule.egg-info/requires.txt
SilverHandTrackingModule.egg-info/top_level.txt