Metadata-Version: 1.1
Name: SilverHandTrackingModule
Version: 1.0.1
Summary: Track the Hands from Web Cam as default
Home-page: https://github.com/Cadris/HandTrackModule
Author: Sayan Dasgupta
Author-email: cadrissilver@gmail.com
License: MIT
Keywords: hand handtracker handtrackermodule
Platform: UNKNOWN
Classifier: Development Status :: 5 - Production/Stable
Classifier: Intended Audience :: Education
Classifier: Operating System :: Microsoft :: Windows :: Windows 10
Classifier: License :: OSI Approved :: MIT License
Classifier: Programming Language :: Python :: 3
